odoo8_addon_mgmtsystem_environment-8.0.1.0.0-py2.7-nspkg.pth
odoo_addons/mgmtsystem_environment/__openerp__.py
odoo_addons/mgmtsystem_environment/environment.xml
odoo_addons/mgmtsystem_environment/__init__.py
odoo_addons/mgmtsystem_environment/README.rst
odoo_addons/mgmtsystem_environment/i18n/tr.po
odoo_addons/mgmtsystem_environment/i18n/nb.po
odoo_addons/mgmtsystem_environment/i18n/mgmtsystem_environment.pot
odoo_addons/mgmtsystem_environment/i18n/de.po
odoo_addons/mgmtsystem_environment/i18n/vi.po
odoo_addons/mgmtsystem_environment/i18n/fr.po
odoo_addons/mgmtsystem_environment/i18n/pt_BR.po
odoo_addons/mgmtsystem_environment/i18n/sv.po
odoo_addons/mgmtsystem_environment/static/description/icon.png
odoo8_addon_mgmtsystem_environment-8.0.1.0.0.dist-info/top_level.txt
odoo8_addon_mgmtsystem_environment-8.0.1.0.0.dist-info/WHEEL
odoo8_addon_mgmtsystem_environment-8.0.1.0.0.dist-info/RECORD
odoo8_addon_mgmtsystem_environment-8.0.1.0.0.dist-info/metadata.json
odoo8_addon_mgmtsystem_environment-8.0.1.0.0.dist-info/DESCRIPTION.rst
odoo8_addon_mgmtsystem_environment-8.0.1.0.0.dist-info/METADATA
odoo8_addon_mgmtsystem_environment-8.0.1.0.0.dist-info/namespace_packages.txt
