Metadata-Version: 2.0
Name: odoo8-addon-mgmtsystem-environment
Version: 8.0.1.0.0
Summary: Environment Management System
Home-page: http://www.savoirfairelinux.com
Author: UNKNOWN
Author-email: UNKNOWN
License: AGPL-3
Platform: UNKNOWN
Requires-Dist: odoo (<9.0a,>=8.0a)
Requires-Dist: odoo8-addon-document-page-environment-manual
Requires-Dist: odoo8-addon-document-page-environmental-aspect
Requires-Dist: odoo8-addon-mgmtsystem-audit
Requires-Dist: odoo8-addon-mgmtsystem-review
Classifier: Programming Language :: Python :: 2.7
Classifier: Framework :: Odoo
Classifier: License :: OSI Approved :: GNU Affero General Public License v3
